<annotation>
	<folder>child_train_labels</folder>
	<filename>child_age_train_pics(104).jpg</filename>
	<path>/child_train_labels/child_age_train_pics(104).jpg</path>
	<source>
		<database>Unspecified</database>
	</source>
	<size>
		<width>240</width>
		<height>208</height>
		<depth>3</depth>
	</size>
	<object>
		<name>child</name>
		<pose>Unspecified</pose>
		<truncated>0</truncated>
		<difficult>0</difficult>
		<bndbox>
			<xmin>2</xmin>
			<ymin>4</ymin>
			<xmax>232</xmax>
			<ymax>183</ymax>
		</bndbox>
	</object>
</annotation>