<annotation>
	<folder>teen_train</folder>
	<filename>teen_age_train_pic(216).jpg</filename>
	<path>/teen_train/teen_age_train_pic(216).jpg</path>
	<source>
		<database>Unspecified</database>
	</source>
	<size>
		<width>626</width>
		<height>626</height>
		<depth>3</depth>
	</size>
	<object>
		<name>teen</name>
		<pose>Unspecified</pose>
		<truncated>0</truncated>
		<difficult>0</difficult>
		<bndbox>
			<xmin>148</xmin>
			<ymin>39</ymin>
			<xmax>468</xmax>
			<ymax>407</ymax>
		</bndbox>
	</object>
</annotation>