<annotation>
	<folder>my-project-name</folder>
	<filename>female_train(58).jpg</filename>
	<path>/my-project-name/female_train(58).jpg</path>
	<source>
		<database>Unspecified</database>
	</source>
	<size>
		<width>957</width>
		<height>1300</height>
		<depth>3</depth>
	</size>
	<object>
		<name>Female</name>
		<pose>Unspecified</pose>
		<truncated>0</truncated>
		<difficult>0</difficult>
		<bndbox>
			<xmin>20</xmin>
			<ymin>39</ymin>
			<xmax>846</xmax>
			<ymax>1090</ymax>
		</bndbox>
	</object>
</annotation>