<annotation>
	<folder>my-project-name</folder>
	<filename>female_train(181).jpg</filename>
	<path>/my-project-name/female_train(181).jpg</path>
	<source>
		<database>Unspecified</database>
	</source>
	<size>
		<width>500</width>
		<height>720</height>
		<depth>3</depth>
	</size>
	<object>
		<name>Female</name>
		<pose>Unspecified</pose>
		<truncated>0</truncated>
		<difficult>0</difficult>
		<bndbox>
			<xmin>41</xmin>
			<ymin>11</ymin>
			<xmax>484</xmax>
			<ymax>513</ymax>
		</bndbox>
	</object>
</annotation>