<annotation>
	<folder>my-project-name</folder>
	<filename>female_train(29).jpg</filename>
	<path>/my-project-name/female_train(29).jpg</path>
	<source>
		<database>Unspecified</database>
	</source>
	<size>
		<width>2121</width>
		<height>1414</height>
		<depth>3</depth>
	</size>
	<object>
		<name>Female</name>
		<pose>Unspecified</pose>
		<truncated>0</truncated>
		<difficult>0</difficult>
		<bndbox>
			<xmin>447</xmin>
			<ymin>13</ymin>
			<xmax>1495</xmax>
			<ymax>964</ymax>
		</bndbox>
	</object>
</annotation>