<annotation>
	<folder>my-project-name</folder>
	<filename>1000 pic (53).jpg</filename>
	<path>/my-project-name/1000 pic (53).jpg</path>
	<source>
		<database>Unspecified</database>
	</source>
	<size>
		<width>1280</width>
		<height>720</height>
		<depth>3</depth>
	</size>
	<object>
		<name>1000 rupee</name>
		<pose>Unspecified</pose>
		<truncated>0</truncated>
		<difficult>0</difficult>
		<bndbox>
			<xmin>38</xmin>
			<ymin>54</ymin>
			<xmax>1242</xmax>
			<ymax>656</ymax>
		</bndbox>
	</object>
</annotation>