<annotation>
	<folder>my-project-name</folder>
	<filename>happy_train_pic(289).jpg</filename>
	<path>/my-project-name/happy_train_pic(289).jpg</path>
	<source>
		<database>Unspecified</database>
	</source>
	<size>
		<width>847</width>
		<height>847</height>
		<depth>3</depth>
	</size>
	<object>
		<name>Happy</name>
		<pose>Unspecified</pose>
		<truncated>0</truncated>
		<difficult>0</difficult>
		<bndbox>
			<xmin>127</xmin>
			<ymin>197</ymin>
			<xmax>707</xmax>
			<ymax>822</ymax>
		</bndbox>
	</object>
</annotation>